tja2fumen/__init__.py
tja2fumen/classes.py
tja2fumen/constants.py
tja2fumen/converters.py
tja2fumen/hp_values.csv
tja2fumen/parsers.py
tja2fumen/writers.py
tja2fumen-0.9.0.dist-info/LICENSE.txt
tja2fumen-0.9.0.dist-info/METADATA
tja2fumen-0.9.0.dist-info/WHEEL
tja2fumen-0.9.0.dist-info/entry_points.txt
tja2fumen-0.9.0.dist-info/top_level.txt
tja2fumen-0.9.0.dist-info/RECORD
