Metadata-Version: 2.1
Name: tja2fumen
Version: 0.9.0
Summary: Convert TJA chart files into fumen (.bin) chart files
License: MIT License
Project-URL: Homepage, https://github.com/vivaria/tja2fumen/
Project-URL: Bug Reports, https://github.com/vivaria/tja2fumen/issues/
Project-URL: Source, https://github.com/vivaria/tja2fumen/
Keywords: taiko,tatsujin,fumen,TJA
Requires-Python: >=3.8
License-File: LICENSE.txt
Provides-Extra: dev
Requires-Dist: pytest ; extra == 'dev'
Requires-Dist: build ; extra == 'dev'
Requires-Dist: pyinstaller ; extra == 'dev'
Requires-Dist: twine ; extra == 'dev'
Requires-Dist: toml-cli ; extra == 'dev'
Requires-Dist: flake8 ; extra == 'dev'
Requires-Dist: pyproject-flake8 ; extra == 'dev'
Requires-Dist: mypy ; extra == 'dev'
Requires-Dist: pylint ; extra == 'dev'
